.gitignore
pytest_yaml/__init__.cpython-313-aarch64-linux-musl.so
pytest_yaml/__init__.pyi
pytest_yaml/_plugin.cpython-313-aarch64-linux-musl.so
pytest_yaml/_plugin.pyi
pytest_yaml/file.cpython-313-aarch64-linux-musl.so
pytest_yaml/file.pyi
pytest_yaml/fixtures.cpython-313-aarch64-linux-musl.so
pytest_yaml/fixtures.pyi
pytest_yaml/hooks.cpython-313-aarch64-linux-musl.so
pytest_yaml/hooks.pyi
pytest_yaml/models.cpython-313-aarch64-linux-musl.so
pytest_yaml/models.pyi
pytest_yaml/plugin.cpython-313-aarch64-linux-musl.so
pytest_yaml/plugin.pyi
pytest_yaml/settings.cpython-313-aarch64-linux-musl.so
pytest_yaml/settings.pyi
pytest_yaml/templates.cpython-313-aarch64-linux-musl.so
pytest_yaml/templates.pyi
pytest_yaml/yaml_case.schema.yaml
pytest_yaml_sanmu-1.1.3.dist-info/METADATA
pytest_yaml_sanmu-1.1.3.dist-info/WHEEL
pytest_yaml_sanmu-1.1.3.dist-info/entry_points.txt
pytest_yaml_sanmu-1.1.3.dist-info/RECORD
