Metadata-Version: 2.1
Name: pytest-yaml-sanmu
Version: 1.1.3
Summary: Pytest plugin for generating test cases with YAML. In test cases, you can use markers, fixtures, variables, and even call Python functions.
Author-Email: dongfangtianyu <7629022+dongfangtianyu@users.noreply.github.com>
Project-URL: Homepage, https://github.com/dongfangtianyu/pytest-yaml-sanmu
Project-URL: Documentation, https://pytest-yaml-doc.pages.dev/
Requires-Python: >=3.12
Requires-Dist: pytest>=8.2.2
Requires-Dist: pyyaml~=6.0.1
Requires-Dist: pydantic<3,>=2.0
Requires-Dist: allure-pytest>=2.13.5
Requires-Dist: pyyaml-include~=1.3.1
Requires-Dist: jsonschema~=4.21.1
Requires-Dist: Jinja2~=3.1.4
